LICENSE
logmixin/__init__.py
logmixin/logmixin.py
logmixin-0.1.4.dist-info/LICENSE
logmixin-0.1.4.dist-info/WHEEL
logmixin-0.1.4.dist-info/METADATA
logmixin-0.1.4.dist-info/RECORD
