Metadata-Version: 2.1
Name: logmixin
Version: 0.1.4
Summary: Defines a mixin class that adds a convenient get_logger method.
Home-page: https://github.com/sammosummo/logmixin
License: MIT
Keywords: logging,mixin,log,logger
Author: Sam Mathias
Requires-Python: >=3.6,<4.0
Classifier: Development Status :: 3 - Alpha
Classifier: Intended Audience :: Developers
Classifier: License :: OSI Approved :: MIT License
Classifier: Operating System :: OS Independent
Classifier: Programming Language :: Python :: 3
Classifier: Programming Language :: Python :: 3.6
Classifier: Programming Language :: Python :: 3.7
Classifier: Programming Language :: Python :: 3.8
Classifier: Programming Language :: Python :: 3.9
Classifier: Programming Language :: Python :: 3.10
Classifier: Programming Language :: Python :: 3.11
Classifier: Programming Language :: Python :: 3
Classifier: Programming Language :: Python :: 3.10
Classifier: Programming Language :: Python :: 3.11
Classifier: Programming Language :: Python :: 3.6
Classifier: Programming Language :: Python :: 3.7
Classifier: Programming Language :: Python :: 3.8
Classifier: Programming Language :: Python :: 3.9
Classifier: Topic :: Software Development :: Libraries :: Python Modules
Project-URL: Documentation, https://github.com/sammosummo/logmixin
Project-URL: Repository, https://github.com/sammosummo/logmixin
